.gitignore
.publish.sh.un~
.setup.py.un~
.update_module_paths.py.un~
LICENSE.txt
README
Scrap
aoisdasd
increment_version.py
oijio
publish.sh
pyqtconsoletest.py
setup.py
untitled.c
update_module_paths.py
version.py
.idea/QuickPython.iml
.idea/QuickPython.time
.idea/encodings.xml
.idea/misc.xml
.idea/modules.xml
.idea/vcs.xml
.idea/workspace.xml
.idea/inspectionProfiles/Project_Default.xml
rp/__init__.py
rp/__main__.py
rp/documentation.py
rp/list_of_modules.py
rp/r.py
rp/ryan_vimrc.py
rp/version.py
rp/web_evaluator.py
rp.egg-info/PKG-INFO
rp.egg-info/SOURCES.txt
rp.egg-info/dependency_links.txt
rp.egg-info/entry_points.txt
rp.egg-info/requires.txt
rp.egg-info/top_level.txt
rp/libs/Pyperclip.py
rp/libs/__init__.py
rp/libs/debug_comment.py
rp/libs/draw_code_minimap.py
rp/libs/graveyard.py
rp/libs/powerpoint_converter.py
rp/libs/profile_vim_plugins.py
rp/libs/pynput_recorder.py
rp/libs/pypi_inspection.py
rp/libs/pytorch_module_explorer.py
rp/libs/rp_black_macchiato.py
rp/libs/stamp_tensor.py
rp/libs/stdin_python_highlighter.py
rp/libs/torch_hooks.py
rp/libs/torch_tools.py
rp/libs/tracetraptest.py
rp/libs/tweenline.py
rp/libs/webeval_dataset.py
rp/libs/../misc/Todo
rp/libs/../misc/claude_bash.sh
rp/libs/../misc/rp_logo.svg
rp/libs/parso/__init__.py
rp/libs/parso/_compatibility.py
rp/libs/parso/cache.py
rp/libs/parso/file_io.py
rp/libs/parso/grammar.py
rp/libs/parso/normalizer.py
rp/libs/parso/parser.py
rp/libs/parso/tree.py
rp/libs/parso/utils.py
rp/libs/parso/../../misc/Todo
rp/libs/parso/../../misc/claude_bash.sh
rp/libs/parso/../../misc/rp_logo.svg
rp/libs/parso/pgen2/__init__.py
rp/libs/parso/pgen2/generator.py
rp/libs/parso/pgen2/grammar_parser.py
rp/libs/parso/pgen2/../../../misc/Todo
rp/libs/parso/pgen2/../../../misc/claude_bash.sh
rp/libs/parso/pgen2/../../../misc/rp_logo.svg
rp/libs/parso/pgen2/../python/grammar26.txt
rp/libs/parso/pgen2/../python/grammar27.txt
rp/libs/parso/pgen2/../python/grammar310.txt
rp/libs/parso/pgen2/../python/grammar311.txt
rp/libs/parso/pgen2/../python/grammar312.txt
rp/libs/parso/pgen2/../python/grammar33.txt
rp/libs/parso/pgen2/../python/grammar34.txt
