Metadata-Version: 1.0
Name: rp
Version: 0.1.1372
Summary: Ryan's Python: IDE + Library + Tools
Home-page: https://github.com/RyannDaGreat/rp
Author: Ryan Burgert
Author-email: ryancentralorg@gmail.com
License: UNKNOWN
Keywords: rp ml ai repl ide image video audio util
Platform: UNKNOWN
